emvcs/__init__.py
emvcs/emvcs.py
emvcs-2.1.dist-info/LICENSE
emvcs-2.1.dist-info/METADATA
emvcs-2.1.dist-info/WHEEL
emvcs-2.1.dist-info/top_level.txt
emvcs-2.1.dist-info/RECORD
